binaries/go-ui-darwin-amd64
binaries/go-ui-darwin-arm64
binaries/go-ui-linux-amd64
binaries/go-ui-linux-arm64
tng_py/__init__.py
tng_py/cli.py
tng_py/save_file.py
tng_py/ui/__init__.py
tng_py/ui/generate_tests_ui.py
tng_py/ui/go_ui_session.py
tng_py/ui/json_session.py
tng_python-0.3.7.dist-info/METADATA
tng_python-0.3.7.dist-info/WHEEL
tng_python-0.3.7.dist-info/entry_points.txt
tng_python-0.3.7.dist-info/licenses/LICENSE
tng_utils/__init__.py
tng_utils/tng_utils.abi3.so
tng_python-0.3.7.dist-info/RECORD
