Metadata-Version: 2.4
Name: tng-python
Version: 0.3.7
Classifier: Development Status :: 4 - Beta
Classifier: Intended Audience :: Developers
Classifier: License :: Other/Proprietary License
Classifier: Programming Language :: Python :: 3
Classifier: Programming Language :: Python :: 3.10
Classifier: Programming Language :: Python :: 3.11
Classifier: Programming Language :: Python :: 3.12
Classifier: Programming Language :: Python :: 3.13
Classifier: Programming Language :: Rust
Requires-Dist: typer>=0.9.0
Requires-Dist: rich>=13.0.0
Requires-Dist: ast2json>=0.2.1
License-File: LICENSE
Summary: TNG Python - Automated Test Generation for Python
Author-email: Binary Dreams LLC <support@tng.sh>
License: Proprietary
Requires-Python: >=3.10
